mongo_operator/__init__.py
mongo_operator/backup_operator.py
mongo_operator/cleanup_operator.py
mongo_operator/command_line.py
mongo_operator/migrate_operator.py
mongo_operator-0.0.4.dist-info/METADATA
mongo_operator-0.0.4.dist-info/WHEEL
mongo_operator-0.0.4.dist-info/entry_points.txt
mongo_operator-0.0.4.dist-info/top_level.txt
mongo_operator-0.0.4.dist-info/RECORD
