Metadata-Version: 2.1
Name: mongo-operator
Version: 0.0.4
Summary: A tool for backup/cleanup/migrate mongo
Home-page: https://github.com/chienfeng0719/mongo-operator
Author: Jimmy Yeh
Author-email: chienfeng0719@hotmail.com
License: UNKNOWN
Platform: UNKNOWN
Classifier: Programming Language :: Python :: 3
Classifier: License :: OSI Approved :: MIT License
Classifier: Operating System :: OS Independent
Requires-Python: >=3.6
